speedtoxify/__init__.py
speedtoxify/onnx.py
speedtoxify/speedtoxify.py
speedtoxify-0.0.3.dist-info/LICENSE
speedtoxify-0.0.3.dist-info/METADATA
speedtoxify-0.0.3.dist-info/WHEEL
speedtoxify-0.0.3.dist-info/top_level.txt
speedtoxify-0.0.3.dist-info/RECORD
