Metadata-Version: 2.1
Name: speedtoxify
Version: 0.0.3
Summary: Wrapper around detoxify package for faster inference using ONNX runtime.
Home-page: https://github.com/andylolu2/speedtoxify
Author: Andy Lo
Author-email: andylolu24@gmail.com
License: UNKNOWN
Platform: UNKNOWN
Classifier: Programming Language :: Python :: 3
Classifier: License :: OSI Approved :: MIT License
Classifier: Operating System :: OS Independent
Requires-Python: >=3.6
License-File: LICENSE
Requires-Dist: detoxify (>=0.4.0)
Requires-Dist: numpy (>=1.22.3)
Requires-Dist: onnx (>=1.11.0)
Requires-Dist: onnxruntime (>=1.10.0)
Requires-Dist: sympy (>=1.10.1)
Requires-Dist: transformers (>=4.17.0)
